sockless.py
sockless-0.9.1.dist-info/DESCRIPTION.rst
sockless-0.9.1.dist-info/METADATA
sockless-0.9.1.dist-info/metadata.json
sockless-0.9.1.dist-info/RECORD
sockless-0.9.1.dist-info/top_level.txt
sockless-0.9.1.dist-info/WHEEL
