Metadata-Version: 2.0
Name: sockless
Version: 0.9.1
Summary: A nicer API around sockets.
Home-page: http://github.com/toastdriven/sockless/
Author: Daniel Lindsley
Author-email: daniel@toastdriven.com
License: BSD
Platform: UNKNOWN
Classifier: Development Status :: 5 - Production/Stable
Classifier: Intended Audience :: Developers
Classifier: License :: OSI Approved :: BSD License
Classifier: Operating System :: OS Independent
Classifier: Programming Language :: Python
Classifier: Programming Language :: Python :: 2
Classifier: Topic :: Internet
Classifier: Topic :: System :: Networking
